{
  "timestamp": "2026-02-26 10:22:33",
  "last_updated": "2026-02-26 10:22:33",
  "all_signals": [
    {
      "stock_name": "🔴 삼성전자 [0.5 @ 2.0-0.4]",
      "sz_value": 2.44,
      "signal": "IN",
      "price_a": 214000.0,
      "price_b": 149400.0,
      "timestamp": "2026-02-26 10:22:33"
    },
    {
      "stock_name": "🔵 코오롱모빌리티그룹(비) [4.5 @ 2.2-0.1]",
      "sz_value": 0.4,
      "signal": "CHK",
      "price_a": 7290.0,
      "price_b": 12200.0,
      "timestamp": "2026-02-26 10:22:33"
    },
    {
      "stock_name": "🟢 태양금속(비) [5 @ 2.1-0.4]",
      "sz_value": 1.82,
      "signal": "CHK",
      "price_a": 3020.0,
      "price_b": 3995.0,
      "timestamp": "2026-02-26 10:22:33"
    },
    {
      "stock_name": "🔵 NPC(비) [5 @ 2.0-0.4]",
      "sz_value": -0.3,
      "signal": "OUT",
      "price_a": 4020.0,
      "price_b": 2465.0,
      "timestamp": "2026-02-26 10:22:33"
    },
    {
      "stock_name": "🔵 대한제당(비) [5 @ 2.0-0.4]",
      "sz_value": 0.11,
      "signal": "OUT",
      "price_a": 2855.0,
      "price_b": 2445.0,
      "timestamp": "2026-02-26 10:22:33"
    },
    {
      "stock_name": "🟠 덕성(비) [5 @ 2.0-0.4]",
      "sz_value": 0.39,
      "signal": "OUT",
      "price_a": 5090.0,
      "price_b": 7100.0,
      "timestamp": "2026-02-26 10:22:33"
    },
    {
      "stock_name": "🔵 코리아써키트(비) [5 @ 2.0-0.4]",
      "sz_value": 1.33,
      "signal": "CHK",
      "price_a": 57300.0,
      "price_b": 17460.0,
      "timestamp": "2026-02-26 10:22:33"
    },
    {
      "stock_name": "🟠 코오롱(비) [5 @ 2.0-0.4]",
      "sz_value": 1.4,
      "signal": "CHK",
      "price_a": 68600.0,
      "price_b": 30350.0,
      "timestamp": "2026-02-26 10:22:33"
    },
    {
      "stock_name": "🔴 현대차 [0.5 @ 2.1-0.3]",
      "sz_value": 2.85,
      "signal": "IN",
      "price_a": 575000.0,
      "price_b": 301500.0,
      "timestamp": "2026-02-26 10:22:33"
    },
    {
      "stock_name": "⚪ 대신증권(비) [5 @ 2.0-0.3]",
      "sz_value": 2.41,
      "signal": "IN",
      "price_a": 47300.0,
      "price_b": 28750.0,
      "timestamp": "2026-02-26 10:22:33"
    },
    {
      "stock_name": "🟢 성신양회(비) [5 @ 2.0-0.4]",
      "sz_value": 0.66,
      "signal": "CHK",
      "price_a": 10020.0,
      "price_b": 11640.0,
      "timestamp": "2026-02-26 10:22:33"
    },
    {
      "stock_name": "🟢 코오롱글로벌(비) [5 @ 2.0-0.4]",
      "sz_value": 1.55,
      "signal": "CHK",
      "price_a": 10180.0,
      "price_b": 15910.0,
      "timestamp": "2026-02-26 10:22:33"
    },
    {
      "stock_name": "🔵 NH투자증권 [1 @ 2.0-0.3]",
      "sz_value": 4.88,
      "signal": "IN",
      "price_a": 36850.0,
      "price_b": 26400.0,
      "timestamp": "2026-02-26 10:22:33"
    },
    {
      "stock_name": "🟢 신풍제약(비) [1.5 @ 2.0-0.4]",
      "sz_value": 0.7,
      "signal": "CHK",
      "price_a": 12160.0,
      "price_b": 19100.0,
      "timestamp": "2026-02-26 10:22:33"
    },
    {
      "stock_name": "⚪ LG전자 [0.5 @ 2.0-0.2]",
      "sz_value": 2.03,
      "signal": "IN",
      "price_a": 143900.0,
      "price_b": 65100.0,
      "timestamp": "2026-02-26 10:22:33"
    },
    {
      "stock_name": "🟢 한화솔루션 [1 @ 2.1-0.3]",
      "sz_value": 3.53,
      "signal": "IN",
      "price_a": 50700.0,
      "price_b": 29050.0,
      "timestamp": "2026-02-26 10:22:33"
    },
    {
      "stock_name": "🟠 세방(비) [2.5 @ 2.0-0.4]",
      "sz_value": 1.48,
      "signal": "CHK",
      "price_a": 16180.0,
      "price_b": 10030.0,
      "timestamp": "2026-02-26 10:22:33"
    },
    {
      "stock_name": "🔵 한화투자증권(비) [5 @ 2.0-0.4]",
      "sz_value": 2.28,
      "signal": "IN",
      "price_a": 9270.0,
      "price_b": 10170.0,
      "timestamp": "2026-02-26 10:22:33"
    },
    {
      "stock_name": "⚪ LG생활건강 [0.5 @ 2.0-0.2]",
      "sz_value": -1.98,
      "signal": "OUT",
      "price_a": 273000.0,
      "price_b": 119800.0,
      "timestamp": "2026-02-26 10:22:33"
    },
    {
      "stock_name": "🔵 아모레퍼시픽 [4.5 @ 2.1-0.3]",
      "sz_value": -0.1,
      "signal": "OUT",
      "price_a": 157100.0,
      "price_b": 53200.0,
      "timestamp": "2026-02-26 10:22:33"
    },
    {
      "stock_name": "🟠 LG화학 [0.5 @ 2.0-0.4]",
      "sz_value": 1.49,
      "signal": "CHK",
      "price_a": 390000.0,
      "price_b": 186000.0,
      "timestamp": "2026-02-26 10:22:33"
    },
    {
      "stock_name": "🔵 아모레G [0.5 @ 2.0-0.4]",
      "sz_value": 0.43,
      "signal": "CHK",
      "price_a": 32800.0,
      "price_b": 13580.0,
      "timestamp": "2026-02-26 10:22:33"
    },
    {
      "stock_name": "🔵 대한항공 [0.04 @ 2.0-0.4]",
      "sz_value": 2.64,
      "signal": "IN",
      "price_a": 28200.0,
      "price_b": 24900.0,
      "timestamp": "2026-02-26 10:22:33"
    },
    {
      "stock_name": "🟠 S-Oil [0.5 @ 2.2-0.3]",
      "sz_value": 2.59,
      "signal": "IN",
      "price_a": 112500.0,
      "price_b": 56600.0,
      "timestamp": "2026-02-26 10:22:33"
    },
    {
      "stock_name": "🔴 한진칼 [1 @ 2.0-0.2]",
      "sz_value": 2.44,
      "signal": "IN",
      "price_a": 172000.0,
      "price_b": 43300.0,
      "timestamp": "2026-02-26 10:22:33"
    },
    {
      "stock_name": "🟢 SK증권(비) [5 @ 2.0-0.4]",
      "sz_value": 3.83,
      "signal": "IN",
      "price_a": 2345.0,
      "price_b": 5010.0,
      "timestamp": "2026-02-26 10:22:33"
    },
    {
      "stock_name": "🔵 한국금융지주 [1 @ 2.0-0.4]",
      "sz_value": 0.95,
      "signal": "CHK",
      "price_a": 265000.0,
      "price_b": 180600.0,
      "timestamp": "2026-02-26 10:22:33"
    },
    {
      "stock_name": "⚪ 티와이홀딩스(비) [5.25 @ 2.3-0.4]",
      "sz_value": 1.29,
      "signal": "CHK",
      "price_a": 3005.0,
      "price_b": 4510.0,
      "timestamp": "2026-02-26 10:22:33"
    },
    {
      "stock_name": "🔵 미래에셋증권 [0.5 @ 2.0-0.3]",
      "sz_value": 2.79,
      "signal": "IN",
      "price_a": 72600.0,
      "price_b": 24700.0,
      "timestamp": "2026-02-26 10:22:33"
    },
    {
      "stock_name": "🔵 동부건설(비) [5 @ 2.0-0.4]",
      "sz_value": 1.83,
      "signal": "CHK",
      "price_a": 9220.0,
      "price_b": 20500.0,
      "timestamp": "2026-02-26 10:22:33"
    },
    {
      "stock_name": "🔵 크라운제과(비) [5 @ 2.2-0.2]",
      "sz_value": 0.63,
      "signal": "CHK",
      "price_a": 8830.0,
      "price_b": 9400.0,
      "timestamp": "2026-02-26 10:22:33"
    },
    {
      "stock_name": "🟢 두산 [0.25 @ 2.0-0.2]",
      "sz_value": 1.37,
      "signal": "CHK",
      "price_a": 1130000.0,
      "price_b": 550000.0,
      "timestamp": "2026-02-26 10:22:33"
    },
    {
      "stock_name": "🟢 남선알미늄(비) [5 @ 2.1-0.4]",
      "sz_value": -0.32,
      "signal": "OUT",
      "price_a": 1217.0,
      "price_b": 13850.0,
      "timestamp": "2026-02-26 10:22:33"
    },
    {
      "stock_name": "🔵 금호석유 [0.5 @ 2.0-0.3]",
      "sz_value": 1.47,
      "signal": "CHK",
      "price_a": 154600.0,
      "price_b": 70200.0,
      "timestamp": "2026-02-26 10:22:33"
    },
    {
      "stock_name": "🔵 넥센(비) [5 @ 2.0-0.3]",
      "sz_value": 1.42,
      "signal": "CHK",
      "price_a": 7140.0,
      "price_b": 4700.0,
      "timestamp": "2026-02-26 10:22:33"
    },
    {
      "stock_name": "🔵 LX하우시스(비) [5 @ 2.0-0.3]",
      "sz_value": 2.58,
      "signal": "IN",
      "price_a": 32050.0,
      "price_b": 17210.0,
      "timestamp": "2026-02-26 10:22:33"
    },
    {
      "stock_name": "🔴 삼성화재 [0.5 @ 2.0-0.4]",
      "sz_value": -0.45,
      "signal": "OUT",
      "price_a": 547500.0,
      "price_b": 416000.0,
      "timestamp": "2026-02-26 10:22:33"
    },
    {
      "stock_name": "🔵 대상홀딩스(비) [5 @ 2.0-0.3]",
      "sz_value": 0.35,
      "signal": "CHK",
      "price_a": 10360.0,
      "price_b": 14890.0,
      "timestamp": "2026-02-26 10:22:33"
    },
    {
      "stock_name": "🔵 SK케미칼 [1 @ 2.6-0.1]",
      "sz_value": 0.42,
      "signal": "CHK",
      "price_a": 69800.0,
      "price_b": 29550.0,
      "timestamp": "2026-02-26 10:22:33"
    },
    {
      "stock_name": "🔵 소프트센(비) [7 @ 2.0-0.3]",
      "sz_value": 0.5,
      "signal": "CHK",
      "price_a": 296.0,
      "price_b": 6250.0,
      "timestamp": "2026-02-26 10:22:33"
    },
    {
      "stock_name": "⚪ 삼성전기 [0.5 @ 2.0-0.4]",
      "sz_value": 2.99,
      "signal": "IN",
      "price_a": 465500.0,
      "price_b": 190100.0,
      "timestamp": "2026-02-26 10:22:33"
    },
    {
      "stock_name": "🔵 노루홀딩스(비) [2 @ 2.0-0.4]",
      "sz_value": 1.03,
      "signal": "CHK",
      "price_a": 27600.0,
      "price_b": 32900.0,
      "timestamp": "2026-02-26 10:22:33"
    },
    {
      "stock_name": "🔵 LG [0.5 @ 2.0-0.4]",
      "sz_value": 1.69,
      "signal": "CHK",
      "price_a": 101500.0,
      "price_b": 78700.0,
      "timestamp": "2026-02-26 10:22:33"
    },
    {
      "stock_name": "🔵 삼성SDI [0.5 @ 2.1-0.4]",
      "sz_value": 1.42,
      "signal": "CHK",
      "price_a": 448500.0,
      "price_b": 248500.0,
      "timestamp": "2026-02-26 10:22:33"
    },
    {
      "stock_name": "🔵 코오롱인더 [1 @ 2.0-0.4]",
      "sz_value": 3.03,
      "signal": "IN",
      "price_a": 67400.0,
      "price_b": 29150.0,
      "timestamp": "2026-02-26 10:22:33"
    },
    {
      "stock_name": "🟢 대원전선(비) [5 @ 2.1-0.4]",
      "sz_value": 2.93,
      "signal": "IN",
      "price_a": 6210.0,
      "price_b": 4515.0,
      "timestamp": "2026-02-26 10:22:33"
    },
    {
      "stock_name": "🔵 태영건설(비) [5 @ 2.0-0.3]",
      "sz_value": -0.39,
      "signal": "OUT",
      "price_a": 1950.0,
      "price_b": 7200.0,
      "timestamp": "2026-02-26 10:22:33"
    },
    {
      "stock_name": "🔵 흥국화재(비) [5 @ 2.0-0.4]",
      "sz_value": 0.81,
      "signal": "CHK",
      "price_a": 5700.0,
      "price_b": 8500.0,
      "timestamp": "2026-02-26 10:22:33"
    },
    {
      "stock_name": "🟢 대호특수강(비) [7 @ 2.1-0.3]",
      "sz_value": 0.36,
      "signal": "CHK",
      "price_a": 1287.0,
      "price_b": 2820.0,
      "timestamp": "2026-02-26 10:22:33"
    },
    {
      "stock_name": "🔵 계양전기(비) [5 @ 2.1-0.4]",
      "sz_value": 2.46,
      "signal": "IN",
      "price_a": 8490.0,
      "price_b": 7310.0,
      "timestamp": "2026-02-26 10:22:33"
    },
    {
      "stock_name": "🟢 한양증권(비) [0.5 @ 2.0-0.3]",
      "sz_value": 1.5,
      "signal": "CHK",
      "price_a": 26950.0,
      "price_b": 24750.0,
      "timestamp": "2026-02-26 10:22:33"
    },
    {
      "stock_name": "🔴 호텔신라 [3 @ 2.0-0.4]",
      "sz_value": 1.0,
      "signal": "CHK",
      "price_a": 48650.0,
      "price_b": 37550.0,
      "timestamp": "2026-02-26 10:22:33"
    },
    {
      "stock_name": "🔴 SK이노베이션 [1 @ 2.0-0.3]",
      "sz_value": 2.09,
      "signal": "IN",
      "price_a": 130100.0,
      "price_b": 77300.0,
      "timestamp": "2026-02-26 10:22:33"
    },
    {
      "stock_name": "🔴 서울식품(비) [5 @ 2.1-0.4]",
      "sz_value": 6.31,
      "signal": "IN",
      "price_a": 257.0,
      "price_b": 1285.0,
      "timestamp": "2026-02-26 10:22:33"
    },
    {
      "stock_name": "🟠 현대건설 [0.5 @ 2.2-0.4]",
      "sz_value": 1.87,
      "signal": "CHK",
      "price_a": 159000.0,
      "price_b": 75800.0,
      "timestamp": "2026-02-26 10:22:33"
    },
    {
      "stock_name": "🔴 DL이앤씨 [1 @ 2.1-0.4]",
      "sz_value": -0.68,
      "signal": "OUT",
      "price_a": 52700.0,
      "price_b": 26600.0,
      "timestamp": "2026-02-26 10:22:33"
    },
    {
      "stock_name": "🔵 GS [1 @ 2.1-0.4]",
      "sz_value": 1.39,
      "signal": "CHK",
      "price_a": 70700.0,
      "price_b": 58600.0,
      "timestamp": "2026-02-26 10:22:33"
    },
    {
      "stock_name": "🔵 금강공업(비) [5 @ 2.0-0.3]",
      "sz_value": 1.16,
      "signal": "CHK",
      "price_a": 5750.0,
      "price_b": 7750.0,
      "timestamp": "2026-02-26 10:22:33"
    },
    {
      "stock_name": "⚪ 대상 [1 @ 2.0-0.4]",
      "sz_value": 0.07,
      "signal": "OUT",
      "price_a": 23200.0,
      "price_b": 17600.0,
      "timestamp": "2026-02-26 10:22:33"
    },
    {
      "stock_name": "🔵 금호건설(비) [5 @ 2.1-0.3]",
      "sz_value": 0.87,
      "signal": "CHK",
      "price_a": 5240.0,
      "price_b": 15150.0,
      "timestamp": "2026-02-26 10:22:33"
    },
    {
      "stock_name": "🟠 CJ제일제당 [1 @ 2.0-0.3]",
      "sz_value": -1.14,
      "signal": "OUT",
      "price_a": 218000.0,
      "price_b": 140300.0,
      "timestamp": "2026-02-26 10:22:33"
    },
    {
      "stock_name": "🟠 SK디스커버리(비) [5 @ 2.0-0.3]",
      "sz_value": 0.82,
      "signal": "CHK",
      "price_a": 61000.0,
      "price_b": 40550.0,
      "timestamp": "2026-02-26 10:22:33"
    },
    {
      "stock_name": "🔵 DL [1 @ 2.0-0.4]",
      "sz_value": 1.71,
      "signal": "CHK",
      "price_a": 51300.0,
      "price_b": 25600.0,
      "timestamp": "2026-02-26 10:22:33"
    },
    {
      "stock_name": "🟢 노루페인트(비) [5 @ 2.2-0.4]",
      "sz_value": 1.05,
      "signal": "CHK",
      "price_a": 9000.0,
      "price_b": 13320.0,
      "timestamp": "2026-02-26 10:22:33"
    },
    {
      "stock_name": "🔵 동양(비) [2.5 @ 2.0-0.4]",
      "sz_value": 2.18,
      "signal": "IN",
      "price_a": 1002.0,
      "price_b": 4695.0,
      "timestamp": "2026-02-26 10:22:33"
    },
    {
      "stock_name": "🔴 한화 [5 @ 2.0-0.4]",
      "sz_value": null,
      "signal": "CHK",
      "price_a": 93000.0,
      "price_b": 42250.0,
      "timestamp": "2026-02-26 10:22:33"
    },
    {
      "stock_name": "🟠 CJ [1 @ 2.0-0.4]",
      "sz_value": 2.6,
      "signal": "IN",
      "price_a": 224500.0,
      "price_b": 100200.0,
      "timestamp": "2026-02-26 10:22:33"
    },
    {
      "stock_name": "🟢 크라운해태홀딩스(비) [5 @ 2.1-0.3]",
      "sz_value": 0.93,
      "signal": "CHK",
      "price_a": 7310.0,
      "price_b": 7900.0,
      "timestamp": "2026-02-26 10:22:33"
    },
    {
      "stock_name": "🟢 롯데칠성 [1 @ 2.1-0.3]",
      "sz_value": -2.3,
      "signal": "OUT",
      "price_a": 141700.0,
      "price_b": 91500.0,
      "timestamp": "2026-02-26 10:22:33"
    },
    {
      "stock_name": "🟠 SK [0.5 @ 2.0-0.2]",
      "sz_value": 1.37,
      "signal": "CHK",
      "price_a": 399000.0,
      "price_b": 286000.0,
      "timestamp": "2026-02-26 10:22:33"
    },
    {
      "stock_name": "🔵 성문전자(비) [5 @ 2.0-0.4]",
      "sz_value": 2.12,
      "signal": "IN",
      "price_a": 1902.0,
      "price_b": 4630.0,
      "timestamp": "2026-02-26 10:22:33"
    },
    {
      "stock_name": "🟢 일양약품(비) [5 @ 2.0-0.4]",
      "sz_value": 0.61,
      "signal": "CHK",
      "price_a": 13050.0,
      "price_b": 12980.0,
      "timestamp": "2026-02-26 10:22:33"
    },
    {
      "stock_name": "🔵 롯데지주 [1 @ 2.6-0.3]",
      "sz_value": 2.21,
      "signal": "CHK",
      "price_a": 36600.0,
      "price_b": 32150.0,
      "timestamp": "2026-02-26 10:22:33"
    },
    {
      "stock_name": "🔵 깨끗한나라(비) [1.5 @ 2.0-0.4]",
      "sz_value": 0.13,
      "signal": "OUT",
      "price_a": 2040.0,
      "price_b": 11440.0,
      "timestamp": "2026-02-26 10:22:33"
    },
    {
      "stock_name": "🔵 유한양행 [1 @ 2.0-0.3]",
      "sz_value": 1.58,
      "signal": "CHK",
      "price_a": 110100.0,
      "price_b": 94900.0,
      "timestamp": "2026-02-26 10:22:33"
    },
    {
      "stock_name": "🟠 부국증권(비) [5 @ 2.0-0.4]",
      "sz_value": 1.2,
      "signal": "CHK",
      "price_a": 97300.0,
      "price_b": 35500.0,
      "timestamp": "2026-02-26 10:22:33"
    },
    {
      "stock_name": "🟠 남양유업(비) [5 @ 2.0-0.4]",
      "sz_value": -1.4,
      "signal": "OUT",
      "price_a": 51300.0,
      "price_b": 36100.0,
      "timestamp": "2026-02-26 10:22:33"
    },
    {
      "stock_name": "🔵 유화증권(비) [5 @ 2.0-0.4]",
      "sz_value": 2.71,
      "signal": "IN",
      "price_a": 4630.0,
      "price_b": 4000.0,
      "timestamp": "2026-02-26 10:22:33"
    },
    {
      "stock_name": "⚪ 삼양사(비) [5 @ 2.3-0.4]",
      "sz_value": -0.4,
      "signal": "OUT",
      "price_a": 51800.0,
      "price_b": 37000.0,
      "timestamp": "2026-02-26 10:22:33"
    },
    {
      "stock_name": "🟢 JW중외제약(비) [5 @ 2.0-0.4]",
      "sz_value": 3.04,
      "signal": "IN",
      "price_a": 36500.0,
      "price_b": 28400.0,
      "timestamp": "2026-02-26 10:22:33"
    },
    {
      "stock_name": "🟠 하이트진로홀딩스(비) [5 @ 2.0-0.3]",
      "sz_value": 0.24,
      "signal": "OUT",
      "price_a": 9820.0,
      "price_b": 11880.0,
      "timestamp": "2026-02-26 10:22:33"
    },
    {
      "stock_name": "🟠 BYC(비) [0.5 @ 2.0-0.4]",
      "sz_value": 0.37,
      "signal": "OUT",
      "price_a": 55800.0,
      "price_b": 29600.0,
      "timestamp": "2026-02-26 10:22:33"
    },
    {
      "stock_name": "🟢 삼양홀딩스(비) [5 @ 2.0-0.3]",
      "sz_value": null,
      "signal": "CHK",
      "price_a": 54118.0,
      "price_b": 83500.0,
      "timestamp": "2026-02-26 10:22:33"
    },
    {
      "stock_name": "🔵 동원시스템즈 [5 @ 2.0-0.3]",
      "sz_value": -0.53,
      "signal": "OUT",
      "price_a": 27300.0,
      "price_b": 17120.0,
      "timestamp": "2026-02-26 10:22:33"
    },
    {
      "stock_name": "⚪ HD현대인프라_건설 [5 @ 2.0-0.3]",
      "sz_value": -1.41,
      "signal": "OUT",
      "price_a": 13800.0,
      "price_b": 118900.0,
      "timestamp": "2026-02-26 10:22:33"
    }
  ],
  "divergent_signals": [
    {
      "stock_name": "🔴 삼성전자 [0.5 @ 2.0-0.4]",
      "sz_value": 2.44,
      "signal": "IN",
      "price_a": 214000.0,
      "price_b": 149400.0,
      "timestamp": "2026-02-26 10:22:33"
    },
    {
      "stock_name": "🔴 현대차 [0.5 @ 2.1-0.3]",
      "sz_value": 2.85,
      "signal": "IN",
      "price_a": 575000.0,
      "price_b": 301500.0,
      "timestamp": "2026-02-26 10:22:33"
    },
    {
      "stock_name": "⚪ 대신증권(비) [5 @ 2.0-0.3]",
      "sz_value": 2.41,
      "signal": "IN",
      "price_a": 47300.0,
      "price_b": 28750.0,
      "timestamp": "2026-02-26 10:22:33"
    },
    {
      "stock_name": "🔵 NH투자증권 [1 @ 2.0-0.3]",
      "sz_value": 4.88,
      "signal": "IN",
      "price_a": 36850.0,
      "price_b": 26400.0,
      "timestamp": "2026-02-26 10:22:33"
    },
    {
      "stock_name": "⚪ LG전자 [0.5 @ 2.0-0.2]",
      "sz_value": 2.03,
      "signal": "IN",
      "price_a": 143900.0,
      "price_b": 65100.0,
      "timestamp": "2026-02-26 10:22:33"
    },
    {
      "stock_name": "🟢 한화솔루션 [1 @ 2.1-0.3]",
      "sz_value": 3.53,
      "signal": "IN",
      "price_a": 50700.0,
      "price_b": 29050.0,
      "timestamp": "2026-02-26 10:22:33"
    },
    {
      "stock_name": "🔵 한화투자증권(비) [5 @ 2.0-0.4]",
      "sz_value": 2.28,
      "signal": "IN",
      "price_a": 9270.0,
      "price_b": 10170.0,
      "timestamp": "2026-02-26 10:22:33"
    },
    {
      "stock_name": "🔵 대한항공 [0.04 @ 2.0-0.4]",
      "sz_value": 2.64,
      "signal": "IN",
      "price_a": 28200.0,
      "price_b": 24900.0,
      "timestamp": "2026-02-26 10:22:33"
    },
    {
      "stock_name": "🟠 S-Oil [0.5 @ 2.2-0.3]",
      "sz_value": 2.59,
      "signal": "IN",
      "price_a": 112500.0,
      "price_b": 56600.0,
      "timestamp": "2026-02-26 10:22:33"
    },
    {
      "stock_name": "🔴 한진칼 [1 @ 2.0-0.2]",
      "sz_value": 2.44,
      "signal": "IN",
      "price_a": 172000.0,
      "price_b": 43300.0,
      "timestamp": "2026-02-26 10:22:33"
    },
    {
      "stock_name": "🟢 SK증권(비) [5 @ 2.0-0.4]",
      "sz_value": 3.83,
      "signal": "IN",
      "price_a": 2345.0,
      "price_b": 5010.0,
      "timestamp": "2026-02-26 10:22:33"
    },
    {
      "stock_name": "🔵 미래에셋증권 [0.5 @ 2.0-0.3]",
      "sz_value": 2.79,
      "signal": "IN",
      "price_a": 72600.0,
      "price_b": 24700.0,
      "timestamp": "2026-02-26 10:22:33"
    },
    {
      "stock_name": "🔵 LX하우시스(비) [5 @ 2.0-0.3]",
      "sz_value": 2.58,
      "signal": "IN",
      "price_a": 32050.0,
      "price_b": 17210.0,
      "timestamp": "2026-02-26 10:22:33"
    },
    {
      "stock_name": "⚪ 삼성전기 [0.5 @ 2.0-0.4]",
      "sz_value": 2.99,
      "signal": "IN",
      "price_a": 465500.0,
      "price_b": 190100.0,
      "timestamp": "2026-02-26 10:22:33"
    },
    {
      "stock_name": "🔵 코오롱인더 [1 @ 2.0-0.4]",
      "sz_value": 3.03,
      "signal": "IN",
      "price_a": 67400.0,
      "price_b": 29150.0,
      "timestamp": "2026-02-26 10:22:33"
    },
    {
      "stock_name": "🟢 대원전선(비) [5 @ 2.1-0.4]",
      "sz_value": 2.93,
      "signal": "IN",
      "price_a": 6210.0,
      "price_b": 4515.0,
      "timestamp": "2026-02-26 10:22:33"
    },
    {
      "stock_name": "🔵 계양전기(비) [5 @ 2.1-0.4]",
      "sz_value": 2.46,
      "signal": "IN",
      "price_a": 8490.0,
      "price_b": 7310.0,
      "timestamp": "2026-02-26 10:22:33"
    },
    {
      "stock_name": "🔴 SK이노베이션 [1 @ 2.0-0.3]",
      "sz_value": 2.09,
      "signal": "IN",
      "price_a": 130100.0,
      "price_b": 77300.0,
      "timestamp": "2026-02-26 10:22:33"
    },
    {
      "stock_name": "🔴 서울식품(비) [5 @ 2.1-0.4]",
      "sz_value": 6.31,
      "signal": "IN",
      "price_a": 257.0,
      "price_b": 1285.0,
      "timestamp": "2026-02-26 10:22:33"
    },
    {
      "stock_name": "🔵 동양(비) [2.5 @ 2.0-0.4]",
      "sz_value": 2.18,
      "signal": "IN",
      "price_a": 1002.0,
      "price_b": 4695.0,
      "timestamp": "2026-02-26 10:22:33"
    },
    {
      "stock_name": "🟠 CJ [1 @ 2.0-0.4]",
      "sz_value": 2.6,
      "signal": "IN",
      "price_a": 224500.0,
      "price_b": 100200.0,
      "timestamp": "2026-02-26 10:22:33"
    },
    {
      "stock_name": "🔵 성문전자(비) [5 @ 2.0-0.4]",
      "sz_value": 2.12,
      "signal": "IN",
      "price_a": 1902.0,
      "price_b": 4630.0,
      "timestamp": "2026-02-26 10:22:33"
    },
    {
      "stock_name": "🔵 유화증권(비) [5 @ 2.0-0.4]",
      "sz_value": 2.71,
      "signal": "IN",
      "price_a": 4630.0,
      "price_b": 4000.0,
      "timestamp": "2026-02-26 10:22:33"
    },
    {
      "stock_name": "🟢 JW중외제약(비) [5 @ 2.0-0.4]",
      "sz_value": 3.04,
      "signal": "IN",
      "price_a": 36500.0,
      "price_b": 28400.0,
      "timestamp": "2026-02-26 10:22:33"
    }
  ]
}